dfnotebook/__init__.py
dfnotebook/_version.py
dfnotebook/kernel/__init__.py
dfnotebook/kernel/__main__.py
dfnotebook/kernel/_version.py
dfnotebook/kernel/dataflow.py
dfnotebook/kernel/dflink.py
dfnotebook/kernel/displayhook.py
dfnotebook/kernel/iostream.py
dfnotebook/kernel/ipkernel.py
dfnotebook/kernel/jstest.py
dfnotebook/kernel/kernelapp.py
dfnotebook/kernel/kernelspec.py
dfnotebook/kernel/safe_attr.py
dfnotebook/kernel/zmqshell.py
dfnotebook/kernel/resources/logo-32x32.png
dfnotebook/kernel/resources/logo-64x64.png
dfnotebook/labextension/build_log.json
dfnotebook/labextension/package.json
dfnotebook/labextension/schemas/@dfnotebook/dfnotebook-extension/package.json.orig
dfnotebook/labextension/schemas/@dfnotebook/dfnotebook-extension/plugin.json
dfnotebook/labextension/schemas/@dfnotebook/dfnotebook-extension/tracker.json
dfnotebook/labextension/static/373c04fd2418f5c77eea.eot
dfnotebook/labextension/static/3f6d3488cf65374f6f67.woff
dfnotebook/labextension/static/79d088064beb3826054f.eot
dfnotebook/labextension/static/8ea8791754915a898a31.woff2
dfnotebook/labextension/static/9674eb1bd55047179038.svg
dfnotebook/labextension/static/9834b82ad26e2a37583d.woff2
dfnotebook/labextension/static/a3b9817780214caf01e8.svg
dfnotebook/labextension/static/af6397503fcefbd61397.ttf
dfnotebook/labextension/static/be0a084962d8066884f7.svg
dfnotebook/labextension/static/cb9e9e693192413cde2b.woff
dfnotebook/labextension/static/cda59d6efffa685830fd.ttf
dfnotebook/labextension/static/dfcells_lib_index_js.d0fb1e7c05874329a607.js
dfnotebook/labextension/static/dfcells_lib_index_js.d0fb1e7c05874329a607.js.map
dfnotebook/labextension/static/dfgraph_lib_index_js.4715a6031daa5a935a79.js
dfnotebook/labextension/static/dfgraph_lib_index_js.4715a6031daa5a935a79.js.map
dfnotebook/labextension/static/dfnotebook_lib_index_js.37a2d9cbd655b340707a.js
dfnotebook/labextension/static/dfnotebook_lib_index_js.37a2d9cbd655b340707a.js.map
dfnotebook-4.2.0b0.dist-info/METADATA
dfnotebook-4.2.0b0.dist-info/WHEEL
dfnotebook-4.2.0b0.dist-info/licenses/LICENSE.md
dfnotebook-4.2.0b0.dist-info/RECORD
