Metadata-Version: 2.4
Name: dfnotebook
Version: 4.2.0b0
Summary: Dataflow Notebook for Jupyter
Project-URL: Homepage, https://github.com/dataflownb/dfnotebook
Author-email: Dataflow Notebook Development Team <dataflownb@users.noreply.github.com>
License: ## BSD 3-Clause License
License-File: LICENSE.md
Keywords: Dataflow,Jupyter,Kernel,Python
Classifier: Framework :: Jupyter
Classifier: Framework :: Jupyter :: JupyterLab
Classifier: Framework :: Jupyter :: JupyterLab :: 4
Classifier: Framework :: Jupyter :: JupyterLab :: Extensions
Classifier: Framework :: Jupyter :: JupyterLab :: Extensions :: Prebuilt
Classifier: Intended Audience :: Developers
Classifier: Intended Audience :: Science/Research
Classifier: License :: OSI Approved :: BSD License
Classifier: Programming Language :: Python
Classifier: Programming Language :: Python :: 3
Classifier: Programming Language :: Python :: 3.9
Classifier: Programming Language :: Python :: 3.10
Classifier: Programming Language :: Python :: 3.11
Classifier: Programming Language :: Python :: 3.12
Classifier: Programming Language :: Python :: 3.13
Requires-Python: >=3.9
Requires-Dist: dfnbutils
Requires-Dist: ipykernel>=6
Requires-Dist: ipython>=8
Requires-Dist: jupyterlab>=4.2
Requires-Dist: nest-asyncio>=1.4
